SMOS.py
SMOS_client.py
SMOS_constants.py
SMOS_data_track.py
SMOS_exceptions.py
SMOS_server.py
SMOS_shared_memory_object.py
SMOS_shared_memory_object_store.py
SMOS_utils.py
SMOS_antony-1.4.2.dist-info/METADATA
SMOS_antony-1.4.2.dist-info/WHEEL
SMOS_antony-1.4.2.dist-info/top_level.txt
SMOS_antony-1.4.2.dist-info/RECORD
