Metadata-Version: 2.1
Name: SMOS-antony
Version: 1.4.2
Summary: A fast shared memory object store.
Home-page: https://github.com/AntonyMei/SharedMemoryObjectStore
Author: Yixuan Mei
Author-email: meiyx19@mails.tsinghua.edu.cn
License: UNKNOWN
Platform: UNKNOWN
Classifier: Programming Language :: Python :: 3
Classifier: License :: OSI Approved :: MIT License
Classifier: Operating System :: OS Independent
Requires-Python: >=3.8
Requires-Dist: numpy
